bells/__init__.py
bells/__main__.py
bells/colors.py
bells/commands/__init__.py
bells/commands/init.py
bells/commands/rec.py
bells/commands/rec_file.py
bells/linker/__init__.py
bells/linker/filepath.py
bells/recording/__init__.py
bells/recording/recorder.py
bells/utils/__init__.py
bells/utils/config.py
bells/utils/get_root.py
bells/utils/require_project.py
bells-0.7.0.dist-info/LICENSE
bells-0.7.0.dist-info/METADATA
bells-0.7.0.dist-info/WHEEL
bells-0.7.0.dist-info/entry_points.txt
bells-0.7.0.dist-info/RECORD
